pygbm/cli.py
pygbm/gbm_simulator.py
pygbm/version.py
source/api.rst
source/conf.py
source/index.rst
source/usage.rst
tests/test.py
dz339_pygbm-1.0.post0.dist-info/LICENSE
dz339_pygbm-1.0.post0.dist-info/METADATA
dz339_pygbm-1.0.post0.dist-info/WHEEL
dz339_pygbm-1.0.post0.dist-info/entry_points.txt
dz339_pygbm-1.0.post0.dist-info/top_level.txt
dz339_pygbm-1.0.post0.dist-info/RECORD
