Metadata-Version: 2.1
Name: dz339-pygbm
Version: 1.0.post0
Summary: A python package to create simulations of geometric browninan motion.
Author-email: Dario Zela <dz339@cam.ac.uk>
License: Copyright (c)  
Project-URL: Documentation, https://pygbmdariodis2024.readthedocs.io/en/latest/#
Project-URL: Source, https://github.com/Dario-Zela/pygbm
Project-URL: Issues, https://github.com/Dario-Zela/pygbm/issues
Keywords: Geometric Brownian Motion,physics,simualtion
Classifier: Development Status :: 4 - Beta
Classifier: License :: OSI Approved :: MIT License
Requires-Python: >=3.12
License-File: LICENSE
Requires-Dist: numpy
Requires-Dist: argparse
Requires-Dist: matplotlib
